gr8pc/__init__.py
gr8pc/__meta__.py
gr8pc/enums.py
gr8pc/exceptions.py
gr8pc/interceptor.py
gr8pc/method.py
gr8pc/middleware.py
gr8pc/models.py
gr8pc/reflection.py
gr8pc/utils.py
gr8pc/proto/__init__.py
gr8pc/proto/enums.py
gr8pc/proto/parser.py
gr8pc/server/__init__.py
gr8pc/server/base.py
gr8pc/service/__init__.py
gr8pc/service/base.py
gr8pc/service/meta.py
gr8pc-0.2.0.dist-info/METADATA
gr8pc-0.2.0.dist-info/WHEEL
gr8pc-0.2.0.dist-info/RECORD
