Metadata-Version: 2.4
Name: gr8pc
Version: 0.2.0
Summary: gr8pc: A High-Level gRPC Wrapper for python
Project-URL: Homepage, https://github.com/lucas-labs/gr8pc
Project-URL: Documentation, https://github.com/lucas-labs/gr8pc
Project-URL: Repository, https://github.com/lucas-labs/gr8pc
Author-email: Lucas Colombo <lucasncolombo@gmail.com>
License-Expression: MIT
Requires-Python: >=3.11
Requires-Dist: grpc-interceptor>=0.15.4
Requires-Dist: grpcio-tools>=1.67.1
Requires-Dist: grpcio>=1.67.1
Requires-Dist: protobuf>=5.28.3
Requires-Dist: pydantic<3
Provides-Extra: reflection
Requires-Dist: grpcio-reflection>=1.76.0; extra == 'reflection'
